database.py
hostname_resolver.py
sytssh.py
sytssh-0.0.6.dist-info/DESCRIPTION.rst
sytssh-0.0.6.dist-info/METADATA
sytssh-0.0.6.dist-info/RECORD
sytssh-0.0.6.dist-info/WHEEL
sytssh-0.0.6.dist-info/entry_points.txt
sytssh-0.0.6.dist-info/metadata.json
sytssh-0.0.6.dist-info/top_level.txt
