Metadata-Version: 2.0
Name: sytssh
Version: 0.0.6
Summary: A ssh helper to save your time
Home-page: https://github.com/felipear89/pyssh
Author: Felipe Alexandre Rodrigues
Author-email: felipear89@gmail.com
License: GNU
Platform: UNKNOWN
Requires-Dist: argcomplete (==1.8.2)
Requires-Dist: argparse (==1.4.0)
Requires-Dist: pyyaml (==3.12)
